{
  "$schema": "https://json-schema.org/draft/2020-12/schema#",
  "description": "[PagedQueryResult](/../api/general-concepts#pagedqueryresult) with results containing an array of [ProductDiscount](ctp:api:type:ProductDiscount).",
  "additionalProperties": false,
  "title": "ProductDiscountPagedQueryResponse",
  "type": "object",
  "properties": {
    "limit": {"type": "number"},
    "count": {"type": "number"},
    "total": {"type": "number"},
    "offset": {"type": "number"},
    "results": {
      "type": "array",
      "items": {"$ref": "ProductDiscount.schema.json"}
    }
  },
  "required": [
    "limit",
    "offset",
    "count",
    "results"
  ],
  "$id": "https://api.commercetools.com/ProductDiscountPagedQueryResponse.schema.json"
}
