{
  "$schema": "https://json-schema.org/draft/2020-12/schema#",
  "description": "[PagedQueryResult](/general-concepts#pagedqueryresult) containing an array of [ProductSelection](ctp:api:type:ProductSelection).",
  "additionalProperties": false,
  "title": "ProductSelectionPagedQueryResponse",
  "type": "object",
  "properties": {
    "limit": {"type": "number"},
    "count": {"type": "number"},
    "total": {"type": "number"},
    "offset": {"type": "number"},
    "results": {
      "type": "array",
      "items": {"$ref": "ProductSelection.schema.json"}
    }
  },
  "required": [
    "limit",
    "offset",
    "count",
    "results"
  ],
  "$id": "https://api.commercetools.com/ProductSelectionPagedQueryResponse.schema.json"
}
