{
  "additionalProperties": false,
  "$schema": "https://json-schema.org/draft/2020-12/schema#",
  "title": "UserProvidedIdentifiers",
  "type": "object",
  "properties": {
    "orderNumber": {"type": "string"},
    "externalId": {"type": "string"},
    "containerAndKey": {"$ref": "ContainerAndKey.schema.json"},
    "customerNumber": {"type": "string"},
    "sku": {"type": "string"},
    "key": {"type": "string"},
    "slug": {"$ref": "LocalizedString.schema.json"}
  },
  "$id": "https://api.commercetools.com/UserProvidedIdentifiers.schema.json"
}
